minireqs/__init__.py
minireqs/__main__.py
minireqs/helpers.py
minireqs/pip_package_extract.py
minireqs-0.5.7.dist-info/licenses/LICENSE
minireqs-0.5.7.dist-info/METADATA
minireqs-0.5.7.dist-info/WHEEL
minireqs-0.5.7.dist-info/top_level.txt
minireqs-0.5.7.dist-info/RECORD
