Metadata-Version: 2.4
Name: minireqs
Version: 0.5.7
Summary: A lightweight Python utility that scans .py files to detect all import statements, identifies the corresponding PyPI packages, and determines their installed version numbers. This tool automatically generates an accurate and minimal requirements.txt (or dependency list), making it ideal for packaging, deployment, and environment reproduction.
Author-email: Lei Liu <dr.mathesis@outlook.com>
License: LICENSE
Project-URL: Homepage, https://github.com/mathesis-universe/minireqs
Requires-Python: >=3.10
License-File: LICENSE
Requires-Dist: numpy>=2.0.0
Requires-Dist: pandas>=2.2.2
Requires-Dist: uv
Provides-Extra: numpy1
Requires-Dist: numpy<2.0.0,>=1.21.0; extra == "numpy1"
Requires-Dist: pandas<2.2.2,>=2.0.0; extra == "numpy1"
Requires-Dist: uv; extra == "numpy1"
Dynamic: license-file
